[
    {
        "domain": ".facebook.com",
        "expirationDate": 1610222685.320521,
        "hostOnly": false,
        "httpOnly": false,
        "name": "c_user",
        "path": "/",
        "sameSite": "no_restriction",
        "secure": true,
        "session": false,
        "storeId": "0",
        "value": "100038437520170",
        "id": 1
    },
    {
        "domain": ".facebook.com",
        "expirationDate": 1610221138.699724,
        "hostOnly": false,
        "httpOnly": true,
        "name": "datr",
        "path": "/",
        "sameSite": "no_restriction",
        "secure": true,
        "session": false,
        "storeId": "0",
        "value": "UbgMX2JCa0xzHMJ26FzntcsR",
        "id": 2
    },
    {
        "domain": ".facebook.com",
        "expirationDate": 1602446683.320872,
        "hostOnly": false,
        "httpOnly": true,
        "name": "fr",
        "path": "/",
        "sameSite": "no_restriction",
        "secure": true,
        "session": false,
        "storeId": "0",
        "value": "1FfFNAy1p6SCPFOqv.AWVPW4l8V0810xY47uLR7PML5XI.BfDLhR.Bb.AAA.0.0.BfDL5c.AWX85vi3",
        "id": 3
    },
    {
        "domain": ".facebook.com",
        "expirationDate": 1595273959.235499,
        "hostOnly": false,
        "httpOnly": false,
        "name": "locale",
        "path": "/",
        "sameSite": "no_restriction",
        "secure": true,
        "session": false,
        "storeId": "0",
        "value": "vi_VN",
        "id": 4
    },
    {
        "domain": ".facebook.com",
        "expirationDate": 1610222685.320344,
        "hostOnly": false,
        "httpOnly": true,
        "name": "sb",
        "path": "/",
        "sameSite": "no_restriction",
        "secure": true,
        "session": false,
        "storeId": "0",
        "value": "UbgMX4qK5INL3xiEiE8q9s3h",
        "id": 5
    },
    {
        "domain": ".facebook.com",
        "expirationDate": 1594760685.710731,
        "hostOnly": false,
        "httpOnly": true,
        "name": "spin",
        "path": "/",
        "sameSite": "no_restriction",
        "secure": true,
        "session": false,
        "storeId": "0",
        "value": "r.1002360775_b.trunk_t.1594670685_s.1_v.2_",
        "id": 6
    },
    {
        "domain": ".facebook.com",
        "expirationDate": 1595275482,
        "hostOnly": false,
        "httpOnly": false,
        "name": "wd",
        "path": "/",
        "sameSite": "no_restriction",
        "secure": true,
        "session": false,
        "storeId": "0",
        "value": "1920x941",
        "id": 7
    },
    {
        "domain": ".facebook.com",
        "expirationDate": 1610222685.320677,
        "hostOnly": false,
        "httpOnly": true,
        "name": "xs",
        "path": "/",
        "sameSite": "no_restriction",
        "secure": true,
        "session": false,
        "storeId": "0",
        "value": "47%3AeX8ODVuIUZg5xw%3A2%3A1594670684%3A5100%3A7309",
        "id": 8
    }
    ]